luckyhomenumber/__init__.py
luckyhomenumber/homenumber.py
luckyhomenumber-0.0.3.dist-info/LICENSE
luckyhomenumber-0.0.3.dist-info/METADATA
luckyhomenumber-0.0.3.dist-info/WHEEL
luckyhomenumber-0.0.3.dist-info/top_level.txt
luckyhomenumber-0.0.3.dist-info/RECORD
