Metadata-Version: 2.1
Name: luckyhomenumber
Version: 0.0.3
Summary: An application to help you find a lucky home address number
Home-page: https://github.com/noppGithub/luckyhomenumber
Author: Nopporn Phantawee
Author-email: n.phantawee@gmail.com
License: MIT License
